string_color-1.3.0.dist-info/licenses/LICENSE
stringcolor/__init__.py
stringcolor/colors.json
stringcolor/main.py
stringcolor/ops.py
string_color-1.3.0.dist-info/METADATA
string_color-1.3.0.dist-info/WHEEL
string_color-1.3.0.dist-info/entry_points.txt
string_color-1.3.0.dist-info/top_level.txt
string_color-1.3.0.dist-info/RECORD
