Metadata-Version: 2.4
Name: string-color
Version: 1.3.0
Summary: just another mod to print strings in 256 colors in the terminal.
Home-page: https://gitlab.com/shindagger/string-color
Author: Andy Klier
Author-email: andyklier@gmail.com
License: MIT
Classifier: Programming Language :: Python :: 3
Classifier: Operating System :: OS Independent
License-File: LICENSE
Requires-Dist: setuptools
Requires-Dist: columnar>=1.3.1
Requires-Dist: colorama
Requires-Dist: importlib_metadata; python_version < "3.8"
Dynamic: author
Dynamic: author-email
Dynamic: classifier
Dynamic: description
Dynamic: description-content-type
Dynamic: home-page
Dynamic: license
Dynamic: license-file
Dynamic: requires-dist
Dynamic: summary
